setup.py
plandf/__init__.py
plandf/plan_maker.py
plandf/rates.py
plandf/settings.py
plandf/utils.py
plandf.egg-info/PKG-INFO
plandf.egg-info/SOURCES.txt
plandf.egg-info/dependency_links.txt
plandf.egg-info/not-zip-safe
plandf.egg-info/requires.txt
plandf.egg-info/top_level.txt
test/test_plandf.py