Metadata-Version: 1.0
Name: plandf
Version: 0.1.127
Summary: Pandas DataFrame for computing Value-Over-Time for lists of tuples (Step.investables, Step.deliverables) of a Plan.
Home-page: https://github.com/WeFindX/PlanDF
Author: Mindey I.
Author-email: desk@infty.xyz
License: MIT
Platform: UNKNOWN
